{
"meta":{"test_sets":[],"test_metrics":[],"learn_metrics":[{"best_value":"Min","name":"RMSE"}],"launch_mode":"Train","parameters":"","iteration_count":300,"learn_sets":["learn"],"name":"experiment"},
"iterations":[
{"learn":[1.620380927],"iteration":0,"passed_time":0.007784371546,"remaining_time":2.327527092},
{"learn":[1.549635458],"iteration":1,"passed_time":0.01413780729,"remaining_time":2.106533287},
{"learn":[1.482425793],"iteration":2,"passed_time":0.02036741859,"remaining_time":2.01637444},
{"learn":[1.418514928],"iteration":3,"passed_time":0.02588961322,"remaining_time":1.915831378},
{"learn":[1.358241077],"iteration":4,"passed_time":0.03161725935,"remaining_time":1.865418302},
{"learn":[1.30197526],"iteration":5,"passed_time":0.03726755704,"remaining_time":1.826110295},
{"learn":[1.248490052],"iteration":6,"passed_time":0.04272510798,"remaining_time":1.788350948},
{"learn":[1.197755382],"iteration":7,"passed_time":0.04888016652,"remaining_time":1.784126078},
{"learn":[1.149955004],"iteration":8,"passed_time":0.05429368642,"remaining_time":1.755495861},
{"learn":[1.105705124],"iteration":9,"passed_time":0.05987459158,"remaining_time":1.736363156},
{"learn":[1.063934787],"iteration":10,"passed_time":0.06594208136,"remaining_time":1.732478319},
{"learn":[1.02503507],"iteration":11,"passed_time":0.07213730597,"remaining_time":1.731295343},
{"learn":[0.988255603],"iteration":12,"passed_time":0.07827397716,"remaining_time":1.728048573},
{"learn":[0.9532294071],"iteration":13,"passed_time":0.08437836635,"remaining_time":1.723729484},
{"learn":[0.9202818067],"iteration":14,"passed_time":0.0901674662,"remaining_time":1.713181858},
{"learn":[0.8892162048],"iteration":15,"passed_time":0.09566855078,"remaining_time":1.698116776},
{"learn":[0.8604786976],"iteration":16,"passed_time":0.1018206007,"remaining_time":1.695013529},
{"learn":[0.8331736938],"iteration":17,"passed_time":0.1069848041,"remaining_time":1.676095264},
{"learn":[0.8078382097],"iteration":18,"passed_time":0.112522214,"remaining_time":1.664144322},
{"learn":[0.7840592161],"iteration":19,"passed_time":0.1182623027,"remaining_time":1.655672238},
{"learn":[0.7620417477],"iteration":20,"passed_time":0.123961218,"remaining_time":1.646913324},
{"learn":[0.7415296148],"iteration":21,"passed_time":0.1292123505,"remaining_time":1.632774247},
{"learn":[0.7227830406],"iteration":22,"passed_time":0.1350170368,"remaining_time":1.626074748},
{"learn":[0.7050146641],"iteration":23,"passed_time":0.1403576693,"remaining_time":1.614113197},
{"learn":[0.6887249334],"iteration":24,"passed_time":0.1454180057,"remaining_time":1.599598062},
{"learn":[0.6735037591],"iteration":25,"passed_time":0.1512199946,"remaining_time":1.593626097},
{"learn":[0.6594076153],"iteration":26,"passed_time":0.1565791071,"remaining_time":1.58318875},
{"learn":[0.646512611],"iteration":27,"passed_time":0.1616802168,"remaining_time":1.57060782},
{"learn":[0.6343178305],"iteration":28,"passed_time":0.1668615685,"remaining_time":1.559292588},
{"learn":[0.62335694],"iteration":29,"passed_time":0.1718903618,"remaining_time":1.547013257},
{"learn":[0.6130522998],"iteration":30,"passed_time":0.1771802669,"remaining_time":1.537467477},
{"learn":[0.6035853023],"iteration":31,"passed_time":0.182671929,"remaining_time":1.529877406},
{"learn":[0.5950834727],"iteration":32,"passed_time":0.1879757172,"remaining_time":1.520894439},
{"learn":[0.5872789197],"iteration":33,"passed_time":0.1931801008,"remaining_time":1.511350201},
{"learn":[0.5798643857],"iteration":34,"passed_time":0.1985256374,"remaining_time":1.503122683},
{"learn":[0.5728464509],"iteration":35,"passed_time":0.2037032098,"remaining_time":1.493823539},
{"learn":[0.566692204],"iteration":36,"passed_time":0.2086335767,"remaining_time":1.482990018},
{"learn":[0.5608674276],"iteration":37,"passed_time":0.2155978303,"remaining_time":1.486490304},
{"learn":[0.5554797615],"iteration":38,"passed_time":0.2204749082,"remaining_time":1.475485924},
{"learn":[0.5505628134],"iteration":39,"passed_time":0.2254548417,"remaining_time":1.465456471},
{"learn":[0.5462158471],"iteration":40,"passed_time":0.2304794946,"remaining_time":1.455955832},
{"learn":[0.5420912224],"iteration":41,"passed_time":0.2356138211,"remaining_time":1.447342044},
{"learn":[0.5384035678],"iteration":42,"passed_time":0.2409232413,"remaining_time":1.439936582},
{"learn":[0.5349633931],"iteration":43,"passed_time":0.2487587818,"remaining_time":1.447323821},
{"learn":[0.5318743093],"iteration":44,"passed_time":0.2539752626,"remaining_time":1.439193155},
{"learn":[0.5289426723],"iteration":45,"passed_time":0.2597584304,"remaining_time":1.43431829},
{"learn":[0.5264528205],"iteration":46,"passed_time":0.2649715008,"remaining_time":1.426335951},
{"learn":[0.5240380783],"iteration":47,"passed_time":0.2697130604,"remaining_time":1.415993567},
{"learn":[0.5219240999],"iteration":48,"passed_time":0.2751726497,"remaining_time":1.409557859},
{"learn":[0.5199416685],"iteration":49,"passed_time":0.2810339635,"remaining_time":1.405169817},
{"learn":[0.5180465718],"iteration":50,"passed_time":0.2867690477,"remaining_time":1.400107703},
{"learn":[0.5164308858],"iteration":51,"passed_time":0.2919915588,"remaining_time":1.392575126},
{"learn":[0.5148482927],"iteration":52,"passed_time":0.2979313271,"remaining_time":1.388472411},
{"learn":[0.513508401],"iteration":53,"passed_time":0.3035584804,"remaining_time":1.382877522},
{"learn":[0.5123125333],"iteration":54,"passed_time":0.3090865769,"remaining_time":1.376840206},
{"learn":[0.5111374972],"iteration":55,"passed_time":0.3151511158,"remaining_time":1.373158433},
{"learn":[0.5100416778],"iteration":56,"passed_time":0.3203154085,"remaining_time":1.365555163},
{"learn":[0.5090334746],"iteration":57,"passed_time":0.3260865917,"remaining_time":1.360568193},
{"learn":[0.5081821917],"iteration":58,"passed_time":0.3311782911,"remaining_time":1.352779121},
{"learn":[0.5073289695],"iteration":59,"passed_time":0.3366714663,"remaining_time":1.346685865},
{"learn":[0.5065970381],"iteration":60,"passed_time":0.3419579502,"remaining_time":1.339802461},
{"learn":[0.5058744889],"iteration":61,"passed_time":0.3476076302,"remaining_time":1.334364774},
{"learn":[0.5052191751],"iteration":62,"passed_time":0.352918483,"remaining_time":1.327645722},
{"learn":[0.5046235234],"iteration":63,"passed_time":0.3585566754,"remaining_time":1.32217774},
{"learn":[0.5040764767],"iteration":64,"passed_time":0.3639872084,"remaining_time":1.315953754},
{"learn":[0.5036339649],"iteration":65,"passed_time":0.3689581096,"remaining_time":1.308124207},
{"learn":[0.5031894731],"iteration":66,"passed_time":0.3741209839,"remaining_time":1.301047601},
{"learn":[0.5027933049],"iteration":67,"passed_time":0.3793749125,"remaining_time":1.294337937},
{"learn":[0.502446582],"iteration":68,"passed_time":0.3845842568,"remaining_time":1.287521208},
{"learn":[0.5021501959],"iteration":69,"passed_time":0.389625262,"remaining_time":1.280197289},
{"learn":[0.5018566977],"iteration":70,"passed_time":0.3949111319,"remaining_time":1.273727454},
{"learn":[0.5015824597],"iteration":71,"passed_time":0.3999213298,"remaining_time":1.266417545},
{"learn":[0.501302897],"iteration":72,"passed_time":0.4050769098,"remaining_time":1.259622719},
{"learn":[0.5010735163],"iteration":73,"passed_time":0.4103569061,"remaining_time":1.253252173},
{"learn":[0.5008532114],"iteration":74,"passed_time":0.4158270818,"remaining_time":1.247481245},
{"learn":[0.5006664573],"iteration":75,"passed_time":0.4203931814,"remaining_time":1.239053587},
{"learn":[0.5004832628],"iteration":76,"passed_time":0.425519399,"remaining_time":1.232348389},
{"learn":[0.5002830839],"iteration":77,"passed_time":0.4305576886,"remaining_time":1.225433421},
{"learn":[0.5001198403],"iteration":78,"passed_time":0.4350681031,"remaining_time":1.21708925},
{"learn":[0.4999464971],"iteration":79,"passed_time":0.43999721,"remaining_time":1.209992328},
{"learn":[0.4998046263],"iteration":80,"passed_time":0.4447743537,"remaining_time":1.202538067},
{"learn":[0.4996616302],"iteration":81,"passed_time":0.4495248375,"remaining_time":1.195078227},
{"learn":[0.4995598878],"iteration":82,"passed_time":0.4543450784,"remaining_time":1.187866048},
{"learn":[0.4994450346],"iteration":83,"passed_time":0.4590138191,"remaining_time":1.180321249},
{"learn":[0.4993387441],"iteration":84,"passed_time":0.4641724397,"remaining_time":1.17408323},
{"learn":[0.4992454486],"iteration":85,"passed_time":0.4692947547,"remaining_time":1.167779971},
{"learn":[0.4991460006],"iteration":86,"passed_time":0.4743691008,"remaining_time":1.161386419},
{"learn":[0.4990450764],"iteration":87,"passed_time":0.4792773825,"remaining_time":1.154622785},
{"learn":[0.4989747487],"iteration":88,"passed_time":0.4843789955,"remaining_time":1.148359192},
{"learn":[0.4989047215],"iteration":89,"passed_time":0.4896614104,"remaining_time":1.142543291},
{"learn":[0.4988307318],"iteration":90,"passed_time":0.4947730509,"remaining_time":1.136346897},
{"learn":[0.4987580487],"iteration":91,"passed_time":0.4996346791,"remaining_time":1.12960884},
{"learn":[0.4986953299],"iteration":92,"passed_time":0.5047550745,"remaining_time":1.123487101},
{"learn":[0.4986457534],"iteration":93,"passed_time":0.5094243811,"remaining_time":1.116398112},
{"learn":[0.4985959784],"iteration":94,"passed_time":0.5142585721,"remaining_time":1.109715866},
{"learn":[0.4985586251],"iteration":95,"passed_time":0.51925329,"remaining_time":1.103413241},
{"learn":[0.4985083088],"iteration":96,"passed_time":0.5239219503,"remaining_time":1.096455216},
{"learn":[0.4984561833],"iteration":97,"passed_time":0.5290651792,"remaining_time":1.090522104},
{"learn":[0.4984191847],"iteration":98,"passed_time":0.5343745103,"remaining_time":1.084942188},
{"learn":[0.4983673397],"iteration":99,"passed_time":0.5392510886,"remaining_time":1.078502177},
{"learn":[0.4983208946],"iteration":100,"passed_time":0.5440352094,"remaining_time":1.071910957},
{"learn":[0.4982766454],"iteration":101,"passed_time":0.54897084,"remaining_time":1.065649278},
{"learn":[0.4982391695],"iteration":102,"passed_time":0.553575803,"remaining_time":1.058780905},
{"learn":[0.4981887179],"iteration":103,"passed_time":0.5578226403,"remaining_time":1.05128113},
{"learn":[0.4981444513],"iteration":104,"passed_time":0.5626927698,"remaining_time":1.045000858},
{"learn":[0.4981011923],"iteration":105,"passed_time":0.5677659896,"remaining_time":1.039118887},
{"learn":[0.4980614062],"iteration":106,"passed_time":0.5723915798,"remaining_time":1.032444625},
{"learn":[0.498031647],"iteration":107,"passed_time":0.5776960262,"remaining_time":1.027015158},
{"learn":[0.497994962],"iteration":108,"passed_time":0.5821155729,"remaining_time":1.02003738},
{"learn":[0.4979630477],"iteration":109,"passed_time":0.5872131925,"remaining_time":1.014277332},
{"learn":[0.4979219693],"iteration":110,"passed_time":0.5928327201,"remaining_time":1.009417875},
{"learn":[0.4978878867],"iteration":111,"passed_time":0.5977034673,"remaining_time":1.003287963},
{"learn":[0.4978470676],"iteration":112,"passed_time":0.6028459728,"remaining_time":0.9976300611},
{"learn":[0.4978115494],"iteration":113,"passed_time":0.607694933,"remaining_time":0.9915022591},
{"learn":[0.4977764298],"iteration":114,"passed_time":0.6124509457,"remaining_time":0.9852471736},
{"learn":[0.4977485988],"iteration":115,"passed_time":0.6173633411,"remaining_time":0.9792659894},
{"learn":[0.4977130635],"iteration":116,"passed_time":0.6223058584,"remaining_time":0.9733501888},
{"learn":[0.4976900684],"iteration":117,"passed_time":0.6273432332,"remaining_time":0.9675971902},
{"learn":[0.4976644515],"iteration":118,"passed_time":0.6315751111,"remaining_time":0.9606310513},
{"learn":[0.4976363567],"iteration":119,"passed_time":0.636326016,"remaining_time":0.9544890241},
{"learn":[0.4976131588],"iteration":120,"passed_time":0.6411413599,"remaining_time":0.9484653176},
{"learn":[0.4975862797],"iteration":121,"passed_time":0.6458229662,"remaining_time":0.9422662949},
{"learn":[0.4975579526],"iteration":122,"passed_time":0.6505844135,"remaining_time":0.936206839},
{"learn":[0.49752793],"iteration":123,"passed_time":0.655238688,"remaining_time":0.9300162024},
{"learn":[0.4975013371],"iteration":124,"passed_time":0.6600061307,"remaining_time":0.924008583},
{"learn":[0.4974766952],"iteration":125,"passed_time":0.6643163377,"remaining_time":0.9173892282},
{"learn":[0.4974499422],"iteration":126,"passed_time":0.669919382,"remaining_time":0.9125673471},
{"learn":[0.4974162852],"iteration":127,"passed_time":0.6748710574,"remaining_time":0.9068579833},
{"learn":[0.4973900031],"iteration":128,"passed_time":0.6794781343,"remaining_time":0.9007035734},
{"learn":[0.4973654948],"iteration":129,"passed_time":0.684933336,"remaining_time":0.8956820548},
{"learn":[0.4973369815],"iteration":130,"passed_time":0.689513232,"remaining_time":0.8895247039},
{"learn":[0.4973062426],"iteration":131,"passed_time":0.6940118591,"remaining_time":0.8832878207},
{"learn":[0.4972834377],"iteration":132,"passed_time":0.6989542215,"remaining_time":0.877634248},
{"learn":[0.4972653615],"iteration":133,"passed_time":0.7037482144,"remaining_time":0.8718074895},
{"learn":[0.4972494335],"iteration":134,"passed_time":0.7087338122,"remaining_time":0.8662302149},
{"learn":[0.4972177892],"iteration":135,"passed_time":0.7130595498,"remaining_time":0.8598659277},
{"learn":[0.4971936426],"iteration":136,"passed_time":0.7179063805,"remaining_time":0.854151387},
{"learn":[0.4971759832],"iteration":137,"passed_time":0.7224783864,"remaining_time":0.8481268015},
{"learn":[0.4971575262],"iteration":138,"passed_time":0.7274583914,"remaining_time":0.8425956907},
{"learn":[0.4971282971],"iteration":139,"passed_time":0.7325237394,"remaining_time":0.8371699879},
{"learn":[0.497097284],"iteration":140,"passed_time":0.737475952,"remaining_time":0.8316218182},
{"learn":[0.4970706854],"iteration":141,"passed_time":0.7424368403,"remaining_time":0.8260916955},
{"learn":[0.4970519561],"iteration":142,"passed_time":0.7476842009,"remaining_time":0.8208840528},
{"learn":[0.4970289348],"iteration":143,"passed_time":0.7525351772,"remaining_time":0.815246442},
{"learn":[0.4970064606],"iteration":144,"passed_time":0.757201534,"remaining_time":0.8094223295},
{"learn":[0.4969783197],"iteration":145,"passed_time":0.7620052134,"remaining_time":0.8037589237},
{"learn":[0.4969500043],"iteration":146,"passed_time":0.7667357551,"remaining_time":0.7980310921},
{"learn":[0.4969293063],"iteration":147,"passed_time":0.7713682364,"remaining_time":0.7922160266},
{"learn":[0.4969036298],"iteration":148,"passed_time":0.7760181515,"remaining_time":0.7864345025},
{"learn":[0.4968826696],"iteration":149,"passed_time":0.7809205504,"remaining_time":0.7809205504},
{"learn":[0.4968591197],"iteration":150,"passed_time":0.7857035716,"remaining_time":0.7752969018},
{"learn":[0.4968303999],"iteration":151,"passed_time":0.7912175684,"remaining_time":0.7703960534},
{"learn":[0.4968192899],"iteration":152,"passed_time":0.7963361964,"remaining_time":0.7651073259},
{"learn":[0.4967922259],"iteration":153,"passed_time":0.8008957753,"remaining_time":0.7592908},
{"learn":[0.4967634699],"iteration":154,"passed_time":0.8060425695,"remaining_time":0.7540398231},
{"learn":[0.496740686],"iteration":155,"passed_time":0.8104521315,"remaining_time":0.7481096598},
{"learn":[0.4967164488],"iteration":156,"passed_time":0.815468531,"remaining_time":0.7427515919},
{"learn":[0.4966886699],"iteration":157,"passed_time":0.8207507046,"remaining_time":0.7376367092},
{"learn":[0.4966683593],"iteration":158,"passed_time":0.8256709305,"remaining_time":0.7321987497},
{"learn":[0.4966455159],"iteration":159,"passed_time":0.8303689624,"remaining_time":0.7265728421},
{"learn":[0.4966227839],"iteration":160,"passed_time":0.8351241374,"remaining_time":0.7210077957},
{"learn":[0.4966026443],"iteration":161,"passed_time":0.8401281698,"remaining_time":0.7156647373},
{"learn":[0.4965825819],"iteration":162,"passed_time":0.8449062275,"remaining_time":0.710135909},
{"learn":[0.4965596009],"iteration":163,"passed_time":0.8499133791,"remaining_time":0.7048062168},
{"learn":[0.4965423684],"iteration":164,"passed_time":0.8544447428,"remaining_time":0.6990911532},
{"learn":[0.4965214325],"iteration":165,"passed_time":0.8594814739,"remaining_time":0.6937982982},
{"learn":[0.4965026178],"iteration":166,"passed_time":0.8641519078,"remaining_time":0.6882167889},
{"learn":[0.4964777825],"iteration":167,"passed_time":0.8697100097,"remaining_time":0.683343579},
{"learn":[0.4964479495],"iteration":168,"passed_time":0.8745134437,"remaining_time":0.6778772847},
{"learn":[0.4964303629],"iteration":169,"passed_time":0.8791643696,"remaining_time":0.672302165},
{"learn":[0.4964014914],"iteration":170,"passed_time":0.8839810118,"remaining_time":0.6668628685},
{"learn":[0.4963826309],"iteration":171,"passed_time":0.8886450192,"remaining_time":0.6613172236},
{"learn":[0.4963567775],"iteration":172,"passed_time":0.8936868629,"remaining_time":0.6560591421},
{"learn":[0.496332619],"iteration":173,"passed_time":0.8987310215,"remaining_time":0.6508052225},
{"learn":[0.4963125684],"iteration":174,"passed_time":0.9037381475,"remaining_time":0.6455272482},
{"learn":[0.4962891745],"iteration":175,"passed_time":0.9088376517,"remaining_time":0.6403174365},
{"learn":[0.4962655785],"iteration":176,"passed_time":0.9140983899,"remaining_time":0.635220915},
{"learn":[0.4962421371],"iteration":177,"passed_time":0.9190267244,"remaining_time":0.6298947212},
{"learn":[0.4962170081],"iteration":178,"passed_time":0.9237531536,"remaining_time":0.6244364893},
{"learn":[0.4961905312],"iteration":179,"passed_time":0.9288681155,"remaining_time":0.6192454103},
{"learn":[0.4961699891],"iteration":180,"passed_time":0.9344225977,"remaining_time":0.6143441388},
{"learn":[0.4961449308],"iteration":181,"passed_time":0.9389422701,"remaining_time":0.6087647685},
{"learn":[0.4961224099],"iteration":182,"passed_time":0.9438671402,"remaining_time":0.6034560404},
{"learn":[0.4960991832],"iteration":183,"passed_time":0.9487928647,"remaining_time":0.5981520234},
{"learn":[0.496078967],"iteration":184,"passed_time":0.9537093727,"remaining_time":0.5928463668},
{"learn":[0.4960544808],"iteration":185,"passed_time":0.9586887532,"remaining_time":0.5875834294},
{"learn":[0.4960382464],"iteration":186,"passed_time":0.9637217701,"remaining_time":0.5823559359},
{"learn":[0.4960133447],"iteration":187,"passed_time":0.96886747,"remaining_time":0.5771976417},
{"learn":[0.4959902608],"iteration":188,"passed_time":0.9734480991,"remaining_time":0.5717076138},
{"learn":[0.4959680321],"iteration":189,"passed_time":0.9785954498,"remaining_time":0.5665552604},
{"learn":[0.4959431414],"iteration":190,"passed_time":0.9840310586,"remaining_time":0.5615674628},
{"learn":[0.4959255869],"iteration":191,"passed_time":0.9893100862,"remaining_time":0.5564869235},
{"learn":[0.4959015318],"iteration":192,"passed_time":0.9948754094,"remaining_time":0.5515630508},
{"learn":[0.4958795879],"iteration":193,"passed_time":0.9996512763,"remaining_time":0.5462012129},
{"learn":[0.4958544682],"iteration":194,"passed_time":1.004502899,"remaining_time":0.5408861764},
{"learn":[0.4958381866],"iteration":195,"passed_time":1.00934077,"remaining_time":0.535568572},
{"learn":[0.4958167985],"iteration":196,"passed_time":1.014306151,"remaining_time":0.5303225051},
{"learn":[0.4957959092],"iteration":197,"passed_time":1.018965178,"remaining_time":0.5249214553},
{"learn":[0.4957818625],"iteration":198,"passed_time":1.0234102,"remaining_time":0.5194192474},
{"learn":[0.4957628538],"iteration":199,"passed_time":1.027851451,"remaining_time":0.5139257257},
{"learn":[0.4957412184],"iteration":200,"passed_time":1.032742529,"remaining_time":0.5086642309},
{"learn":[0.4957223608],"iteration":201,"passed_time":1.037711806,"remaining_time":0.5034443416},
{"learn":[0.4957000062],"iteration":202,"passed_time":1.042833166,"remaining_time":0.4982995915},
{"learn":[0.4956787976],"iteration":203,"passed_time":1.048589934,"remaining_time":0.4934540866},
{"learn":[0.4956630354],"iteration":204,"passed_time":1.053356754,"remaining_time":0.4881409349},
{"learn":[0.4956380235],"iteration":205,"passed_time":1.058396978,"remaining_time":0.4829578445},
{"learn":[0.4956153688],"iteration":206,"passed_time":1.062958161,"remaining_time":0.477560913},
{"learn":[0.4955981959],"iteration":207,"passed_time":1.067988749,"remaining_time":0.472379639},
{"learn":[0.4955832904],"iteration":208,"passed_time":1.072779896,"remaining_time":0.4670955529},
{"learn":[0.4955599097],"iteration":209,"passed_time":1.077923189,"remaining_time":0.4619670812},
{"learn":[0.4955461846],"iteration":210,"passed_time":1.082650344,"remaining_time":0.4566629414},
{"learn":[0.4955252429],"iteration":211,"passed_time":1.087435054,"remaining_time":0.4513881355},
{"learn":[0.4955070032],"iteration":212,"passed_time":1.092284903,"remaining_time":0.4461445377},
{"learn":[0.4954847439],"iteration":213,"passed_time":1.097492726,"remaining_time":0.4410484787},
{"learn":[0.4954566039],"iteration":214,"passed_time":1.102668016,"remaining_time":0.435938518},
{"learn":[0.4954330755],"iteration":215,"passed_time":1.107669973,"remaining_time":0.4307605449},
{"learn":[0.495415416],"iteration":216,"passed_time":1.112828629,"remaining_time":0.4256441299},
{"learn":[0.495404769],"iteration":217,"passed_time":1.117662698,"remaining_time":0.4204052349},
{"learn":[0.4953799356],"iteration":218,"passed_time":1.122645189,"remaining_time":0.4152249329},
{"learn":[0.4953592114],"iteration":219,"passed_time":1.127220548,"remaining_time":0.4098983811},
{"learn":[0.4953450455],"iteration":220,"passed_time":1.131960582,"remaining_time":0.4046374931},
{"learn":[0.4953260374],"iteration":221,"passed_time":1.136522069,"remaining_time":0.3993185646},
{"learn":[0.4953062653],"iteration":222,"passed_time":1.141432016,"remaining_time":0.3941267501},
{"learn":[0.4952812855],"iteration":223,"passed_time":1.146876294,"remaining_time":0.3891187426},
{"learn":[0.4952651076],"iteration":224,"passed_time":1.151827278,"remaining_time":0.3839424259},
{"learn":[0.4952538243],"iteration":225,"passed_time":1.156786444,"remaining_time":0.3787707825},
{"learn":[0.4952274736],"iteration":226,"passed_time":1.162144094,"remaining_time":0.3737291581},
{"learn":[0.4952051408],"iteration":227,"passed_time":1.168097064,"remaining_time":0.368872757},
{"learn":[0.4951868484],"iteration":228,"passed_time":1.173420918,"remaining_time":0.3638117257},
{"learn":[0.4951728963],"iteration":229,"passed_time":1.179005252,"remaining_time":0.3588276854},
{"learn":[0.4951466466],"iteration":230,"passed_time":1.184477922,"remaining_time":0.3538050937},
{"learn":[0.4951320519],"iteration":231,"passed_time":1.189467029,"remaining_time":0.3486368878},
{"learn":[0.4951162261],"iteration":232,"passed_time":1.194012533,"remaining_time":0.3433426598},
{"learn":[0.4950912043],"iteration":233,"passed_time":1.199548093,"remaining_time":0.3383340776},
{"learn":[0.4950622988],"iteration":234,"passed_time":1.205573574,"remaining_time":0.3334565205},
{"learn":[0.4950462457],"iteration":235,"passed_time":1.210701684,"remaining_time":0.3283258803},
{"learn":[0.4950304452],"iteration":236,"passed_time":1.215626049,"remaining_time":0.3231411015},
{"learn":[0.4950054168],"iteration":237,"passed_time":1.220667782,"remaining_time":0.3179890861},
{"learn":[0.4949825053],"iteration":238,"passed_time":1.225387432,"remaining_time":0.3127557882},
{"learn":[0.4949644268],"iteration":239,"passed_time":1.229644871,"remaining_time":0.3074112178},
{"learn":[0.4949480998],"iteration":240,"passed_time":1.234720249,"remaining_time":0.3022759117},
{"learn":[0.4949276519],"iteration":241,"passed_time":1.23945497,"remaining_time":0.2970594556},
{"learn":[0.4949059033],"iteration":242,"passed_time":1.244286613,"remaining_time":0.2918696993},
{"learn":[0.4948794763],"iteration":243,"passed_time":1.249519336,"remaining_time":0.2867749295},
{"learn":[0.4948628408],"iteration":244,"passed_time":1.254456254,"remaining_time":0.2816126284},
{"learn":[0.4948294951],"iteration":245,"passed_time":1.259469636,"remaining_time":0.2764689445},
{"learn":[0.4948090538],"iteration":246,"passed_time":1.264847605,"remaining_time":0.2714045468},
{"learn":[0.4947867408],"iteration":247,"passed_time":1.269743124,"remaining_time":0.2662364614},
{"learn":[0.494755665],"iteration":248,"passed_time":1.274887872,"remaining_time":0.2611216124},
{"learn":[0.4947313019],"iteration":249,"passed_time":1.280313778,"remaining_time":0.2560627557},
{"learn":[0.4947018659],"iteration":250,"passed_time":1.28569715,"remaining_time":0.2509926708},
{"learn":[0.4946823055],"iteration":251,"passed_time":1.290026418,"remaining_time":0.2457193177},
{"learn":[0.494659549],"iteration":252,"passed_time":1.295067502,"remaining_time":0.2405856625},
{"learn":[0.4946362269],"iteration":253,"passed_time":1.299266968,"remaining_time":0.235300317},
{"learn":[0.4946185509],"iteration":254,"passed_time":1.303872809,"remaining_time":0.2300952016},
{"learn":[0.4946029434],"iteration":255,"passed_time":1.308251936,"remaining_time":0.2248558015},
{"learn":[0.494572903],"iteration":256,"passed_time":1.314169557,"remaining_time":0.2198805095},
{"learn":[0.4945539921],"iteration":257,"passed_time":1.318805755,"remaining_time":0.214689309},
{"learn":[0.4945298137],"iteration":258,"passed_time":1.323911819,"remaining_time":0.2095767744},
{"learn":[0.4945111891],"iteration":259,"passed_time":1.329230434,"remaining_time":0.2044969899},
{"learn":[0.4944882958],"iteration":260,"passed_time":1.334018405,"remaining_time":0.1993360835},
{"learn":[0.4944634975],"iteration":261,"passed_time":1.3385301,"remaining_time":0.1941379535},
{"learn":[0.4944439419],"iteration":262,"passed_time":1.343753607,"remaining_time":0.1890451842},
{"learn":[0.4944251319],"iteration":263,"passed_time":1.348072464,"remaining_time":0.1838280632},
{"learn":[0.4944039538],"iteration":264,"passed_time":1.352568895,"remaining_time":0.1786411747},
{"learn":[0.494382446],"iteration":265,"passed_time":1.35726482,"remaining_time":0.173484977},
{"learn":[0.4943657697],"iteration":266,"passed_time":1.361728209,"remaining_time":0.1683034865},
{"learn":[0.4943441634],"iteration":267,"passed_time":1.366310138,"remaining_time":0.1631415091},
{"learn":[0.4943214856],"iteration":268,"passed_time":1.370801383,"remaining_time":0.1579733936},
{"learn":[0.4942995793],"iteration":269,"passed_time":1.375374585,"remaining_time":0.1528193983},
{"learn":[0.4942774358],"iteration":270,"passed_time":1.379475702,"remaining_time":0.1476191711},
{"learn":[0.494255618],"iteration":271,"passed_time":1.384232856,"remaining_time":0.1424945587},
{"learn":[0.4942325466],"iteration":272,"passed_time":1.388385372,"remaining_time":0.137312839},
{"learn":[0.4942136639],"iteration":273,"passed_time":1.393244145,"remaining_time":0.1322056488},
{"learn":[0.4941915868],"iteration":274,"passed_time":1.397900656,"remaining_time":0.1270818779},
{"learn":[0.4941744],"iteration":275,"passed_time":1.402458891,"remaining_time":0.121952947},
{"learn":[0.4941510445],"iteration":276,"passed_time":1.407123108,"remaining_time":0.1168369367},
{"learn":[0.4941294212],"iteration":277,"passed_time":1.412048598,"remaining_time":0.1117448531},
{"learn":[0.4941038821],"iteration":278,"passed_time":1.41687815,"remaining_time":0.1066467425},
{"learn":[0.4940767137],"iteration":279,"passed_time":1.421913134,"remaining_time":0.1015652238},
{"learn":[0.4940555965],"iteration":280,"passed_time":1.427051541,"remaining_time":0.09649102944},
{"learn":[0.4940341918],"iteration":281,"passed_time":1.43156854,"remaining_time":0.09137671531},
{"learn":[0.4940059484],"iteration":282,"passed_time":1.436380164,"remaining_time":0.08628432082},
{"learn":[0.4939860777],"iteration":283,"passed_time":1.44195995,"remaining_time":0.08123718028},
{"learn":[0.4939596359],"iteration":284,"passed_time":1.44643559,"remaining_time":0.07612818897},
{"learn":[0.4939382994],"iteration":285,"passed_time":1.451142565,"remaining_time":0.07103495075},
{"learn":[0.4939167723],"iteration":286,"passed_time":1.455969402,"remaining_time":0.06594983356},
{"learn":[0.4938973514],"iteration":287,"passed_time":1.46071949,"remaining_time":0.06086331209},
{"learn":[0.493877581],"iteration":288,"passed_time":1.465438041,"remaining_time":0.05577791851},
{"learn":[0.4938575786],"iteration":289,"passed_time":1.46964516,"remaining_time":0.0506774193},
{"learn":[0.4938275747],"iteration":290,"passed_time":1.474552247,"remaining_time":0.04560470866},
{"learn":[0.4938087618],"iteration":291,"passed_time":1.479170295,"remaining_time":0.04052521357},
{"learn":[0.4937883101],"iteration":292,"passed_time":1.484132368,"remaining_time":0.03545708728},
{"learn":[0.4937704572],"iteration":293,"passed_time":1.489186704,"remaining_time":0.03039156538},
{"learn":[0.4937518182],"iteration":294,"passed_time":1.493792605,"remaining_time":0.02531851873},
{"learn":[0.493724903],"iteration":295,"passed_time":1.498509498,"remaining_time":0.02025012836},
{"learn":[0.4937019653],"iteration":296,"passed_time":1.502954001,"remaining_time":0.01518135355},
{"learn":[0.4936833807],"iteration":297,"passed_time":1.507347827,"remaining_time":0.01011642837},
{"learn":[0.4936638189],"iteration":298,"passed_time":1.51163969,"remaining_time":0.005055651137},
{"learn":[0.4936456783],"iteration":299,"passed_time":1.516099351,"remaining_time":0}
]}